dltlint/__init__.py
dltlint/__main__.py
dltlint/cli.py
dltlint/config.py
dltlint/core.py
dltlint/models.py
dltlint/py.typed
dltlint/registry.py
dltlint-0.3.6.dist-info/METADATA
dltlint-0.3.6.dist-info/WHEEL
dltlint-0.3.6.dist-info/entry_points.txt
dltlint-0.3.6.dist-info/RECORD
