Metadata-Version: 2.4
Name: dltlint
Version: 0.3.6
Summary: Linter for Databricks DLT pipelines
Project-URL: Homepage, https://github.com/dan1elt0m/dltlint
Project-URL: Issues, https://github.com/dan1elt0m/dltlint/issues
Author-email: Daniel Tom <detom89@gmail.com>
Requires-Python: >=3.10
Requires-Dist: pydantic>=2
Requires-Dist: pyyaml>=6
Requires-Dist: tomli>=2.2
Provides-Extra: dev
Requires-Dist: pre-commit; extra == 'dev'
Requires-Dist: pytest; extra == 'dev'
Requires-Dist: pytest-cov; extra == 'dev'
Requires-Dist: ruff==0.14.10; extra == 'dev'
